xirt/__init__.py
xirt/__main__.py
xirt/_version.py
xirt/const.py
xirt/features.py
xirt/predictor.py
xirt/processing.py
xirt/qc.py
xirt/sequences.py
xirt/xirtnet.py
xiRT-1.2.41.dist-info/LICENCE
xiRT-1.2.41.dist-info/METADATA
xiRT-1.2.41.dist-info/WHEEL
xiRT-1.2.41.dist-info/entry_points.txt
xiRT-1.2.41.dist-info/top_level.txt
xiRT-1.2.41.dist-info/RECORD
