Metadata-Version: 2.1
Name: xiRT
Version: 1.2.41
Summary: xiRT: Multi-dimensional Retention Time Prediction for Linear and Crosslinked Peptides.
Home-page: UNKNOWN
Author: Sven Giese
Author-email: sven.giese@hpi.de
License: Apache License 2.0
Project-URL: Bug Tracker, https://github.com/Rappsilber-Laboratory/xiRT/issues
Project-URL: Source Code, https://github.com/Rappsilber-Laboratory/xiRT
Project-URL: Documentation, https://xirt.readthedocs.io/en/latest/
Project-URL: Homepage, https://rappsilber-laboratory.github.io/xiRT/
Project-URL: Related Software, https://www.rappsilberlab.org/software/
Keywords: xiRT,Proteomics,Crosslinking,machine learning,Retention Time Prediction,Chromatography,Peptides
Platform: UNKNOWN
Classifier: Programming Language :: Python
Classifier: Programming Language :: Python :: 3.8
Classifier: Programming Language :: Python :: Implementation :: PyPy
Requires-Python: >=3.6.0
Requires-Dist: numpy
Requires-Dist: pandas
Requires-Dist: tensorflow
Requires-Dist: seaborn
Requires-Dist: xlwt
Requires-Dist: pyyaml
Requires-Dist: pyteomics
Requires-Dist: sklearn
Requires-Dist: tqdm
Requires-Dist: biopython
Requires-Dist: palettable
Requires-Dist: statannot
Requires-Dist: tensorflow-addons
